brainsets/__init__.py
brainsets/core.py
brainsets/descriptions.py
brainsets/_cli/__init__.py
brainsets/_cli/cli.py
brainsets/_cli/cli_config.py
brainsets/_cli/cli_list.py
brainsets/_cli/cli_prepare.py
brainsets/_cli/utils.py
brainsets/processing/__init__.py
brainsets/processing/signal.py
brainsets/taxonomy/__init__.py
brainsets/taxonomy/allen.py
brainsets/taxonomy/drifting_gratings.py
brainsets/taxonomy/homosapiens.py
brainsets/taxonomy/macaque.py
brainsets/taxonomy/mice.py
brainsets/taxonomy/recording_tech.py
brainsets/taxonomy/speech.py
brainsets/taxonomy/subject.py
brainsets/taxonomy/task.py
brainsets/taxonomy/writing.py
brainsets/utils/__init__.py
brainsets/utils/dandi_utils.py
brainsets/utils/dir_utils.py
brainsets/utils/mat_utils.py
brainsets/utils/split.py
brainsets-0.1.2.dist-info/licenses/LICENSE
brainsets_pipelines/churchland_shenoy_neural_2012/Snakefile
brainsets_pipelines/churchland_shenoy_neural_2012/prepare_data.py
brainsets_pipelines/churchland_shenoy_neural_2012/requirements.txt
brainsets_pipelines/flint_slutzky_accurate_2012/Snakefile
brainsets_pipelines/flint_slutzky_accurate_2012/prepare_data.py
brainsets_pipelines/flint_slutzky_accurate_2012/requirements.txt
brainsets_pipelines/odoherty_sabes_nonhuman_2017/Snakefile
brainsets_pipelines/odoherty_sabes_nonhuman_2017/prepare_data.py
brainsets_pipelines/odoherty_sabes_nonhuman_2017/requirements.txt
brainsets_pipelines/pei_pandarinath_nlb_2021/Snakefile
brainsets_pipelines/pei_pandarinath_nlb_2021/prepare_data.py
brainsets_pipelines/pei_pandarinath_nlb_2021/requirements.txt
brainsets_pipelines/perich_miller_population_2018/Snakefile
brainsets_pipelines/perich_miller_population_2018/prepare_data.py
brainsets_pipelines/perich_miller_population_2018/requirements.txt
brainsets-0.1.2.dist-info/METADATA
brainsets-0.1.2.dist-info/WHEEL
brainsets-0.1.2.dist-info/entry_points.txt
brainsets-0.1.2.dist-info/top_level.txt
brainsets-0.1.2.dist-info/RECORD
