Metadata-Version: 2.4
Name: brainsets
Version: 0.1.2
Summary: A package for processing neural datasets
Author-email: Mehdi Azabou <mehdiazabou@gmail.com>
License: MIT
Project-URL: Homepage, https://github.com/neuro-galaxy/brainsets
Project-URL: Issues, https://github.com/neuro-galaxy/brainsets/issues
Project-URL: Documentation, https://brainsets.readthedocs.io/en/latest/
Classifier: Programming Language :: Python :: 3
Classifier: License :: OSI Approved :: MIT License
Classifier: Operating System :: OS Independent
Requires-Python: >=3.8
License-File: LICENSE
Requires-Dist: temporaldata
Requires-Dist: scipy~=1.10.1
Requires-Dist: pynwb~=2.2.0
Requires-Dist: setuptools~=60.2.0
Requires-Dist: numpy~=1.23.5
Requires-Dist: pandas~=1.5.3
Requires-Dist: jsonschema~=4.21.1
Requires-Dist: scikit-image~=0.19.3
Requires-Dist: tqdm~=4.64.1
Requires-Dist: rich==13.3.2
Requires-Dist: msgpack~=1.0.5
Requires-Dist: snakemake~=7.32.3
Requires-Dist: pydantic~=2.0
Requires-Dist: pulp==2.7.0
Requires-Dist: click~=8.1.3
Requires-Dist: uv
Requires-Dist: prompt_toolkit
Provides-Extra: dev
Requires-Dist: pytest~=7.2.1; extra == "dev"
Requires-Dist: black==24.2.0; extra == "dev"
Requires-Dist: pre-commit>=3.5.0; extra == "dev"
Requires-Dist: flake8; extra == "dev"
Dynamic: license-file
